pydetails/__init__.py
pydetails/cli.py
pydetails/utils.py
pydetails-0.0.2.dist-info/licenses/LICENSE
pydetails-0.0.2.dist-info/METADATA
pydetails-0.0.2.dist-info/WHEEL
pydetails-0.0.2.dist-info/entry_points.txt
pydetails-0.0.2.dist-info/top_level.txt
pydetails-0.0.2.dist-info/RECORD
